holon/__init__.py
holon/base.py
holon/conventions/__init__.py
holon/conventions/case.py
holon/conventions/json.py
holon/conventions/uri.py
holon/design_system.py
holon/formats/__init__.py
holon/formats/alps.py
holon/formats/openapi.py
holon/ietf/__init__.py
holon/ietf/rfc2119.py
holon/ietf/rfc7232.py
holon/models/__init__.py
holon/models/rmm.py
holon/models/wadm.py
holon/principles.py
holon/protocols/__init__.py
holon/protocols/http.py
holon-0.1.1.dist-info/WHEEL
holon-0.1.1.dist-info/METADATA
holon-0.1.1.dist-info/RECORD
