Metadata-Version: 2.1
Name: holon
Version: 0.1.1
Summary: Experimental API Design Dystem library
Home-page: https://github.com/smizell/holon
License: MIT
Author: Stephen Mizell
Author-email: smizell@gmail.com
Requires-Python: >3.6
Classifier: License :: OSI Approved :: MIT License
Classifier: Programming Language :: Python :: 3
Classifier: Programming Language :: Python :: 3.7
Classifier: Programming Language :: Python :: 3.8
Classifier: Programming Language :: Python :: 3.9
Requires-Dist: pydantic (>=1.7.2,<2.0.0)
Project-URL: Repository, https://github.com/smizell/holon
